[{"idBoard":1,"Title":"Test","UrlStandard":"#/Test01"},{"idBoard":2,"Title":"공지","UrlStandard":"#/Notice"},{"idBoard":3,"Title":"음악","UrlStandard":"#/Music"},{"idBoard":4,"Title":"스포츠","UrlStandard":"#/Sports"},{"idBoard":5,"Title":"게임","UrlStandard":"#/Game"},{"idBoard":6,"Title":"영화","UrlStandard":"#/Movie"},{"idBoard":7,"Title":"뉴스","UrlStandard":"#/News"},{"idBoard":8,"Title":"비트코인","UrlStandard":"#/BitCoin"},{"idBoard":9,"Title":"패션","UrlStandard":"#/Fashion"},{"idBoard":10,"Title":"자동차","UrlStandard":"#/Car"},{"idBoard":11,"Title":"야동","UrlStandard":"#/Porn"},{"idBoard":12,"Title":"Q&A","UrlStandard":"#/QnA"},{"idBoard":13,"Title":"d","UrlStandard":null},{"idBoard":14,"Title":"TEST","UrlStandard":null},{"idBoard":15,"Title":"홍보","UrlStandard":null},{"idBoard":16,"Title":"즐겨찾기","UrlStandard":null}]